README.rst
setup.cfg
setup.py
awspycli/__init__.py
awspycli.egg-info/PKG-INFO
awspycli.egg-info/SOURCES.txt
awspycli.egg-info/dependency_links.txt
awspycli.egg-info/requires.txt
awspycli.egg-info/top_level.txt
awspycli.egg-info/zip-safe
awspycli/model/__init__.py
awspycli/model/emr_cli.py
awspycli/model/s3_cli.py