Metadata-Version: 1.0
Name: awspycli
Version: 1.0.2.1
Summary: using python code to communicate with aws client
Home-page: https://github.com/MrLawes/awspycli
Author: Lawes
Author-email: haiou_chen@sina.cn
License: MIT
Platform: UNKNOWN
